ezpykit/__init__.py
ezpykit/allinone.py
ezpykit/call.py
ezpykit/config.py
ezpykit/setup.py
ezpykit/builtin/__init__.py
ezpykit/builtin/_dict.py
ezpykit/builtin/_list.py
ezpykit/builtin/_str.py
ezpykit/const/__init__.py
ezpykit/const/color.py
ezpykit/metautil/__init__.py
ezpykit/metautil/singleton.py
ezpykit/metautil/timer.py
ezpykit/stdlib/__init__.py
ezpykit/stdlib/argparse.py
ezpykit/stdlib/base64.py
ezpykit/stdlib/datetime.py
ezpykit/stdlib/glob.py
ezpykit/stdlib/re.py
ezpykit/stdlib/threading.py
ezpykit/stdlib/typing.py
ezpykit/stdlib/http/__init__.py
ezpykit/stdlib/http/cookiejar.py
ezpykit/stdlib/http/cookiejar_backport_from_cpython_v_3_10.py
ezpykit/stdlib/io/__init__.py
ezpykit/stdlib/io/slicefileio.py
ezpykit/stdlib/io/virtualfileio.py
ezpykit/stdlib/os/__init__.py
ezpykit/stdlib/os/common.py
ezpykit/stdlib/os/nt.py
ezpykit/stdlib/os/posix.py
ezpykit/stdlib/shutil/__deprecated__.py
ezpykit/stdlib/shutil/__init__.py
ezpykit/stdlib/shutil/patch_copyfileobj_lame.py
ezpykit/stdlib/urllib/__init__.py
ezpykit/stdlib/urllib/parse.py
ezpykit-0.1a0.dev202203161630.dist-info/LICENSE
ezpykit-0.1a0.dev202203161630.dist-info/METADATA
ezpykit-0.1a0.dev202203161630.dist-info/WHEEL
ezpykit-0.1a0.dev202203161630.dist-info/top_level.txt
ezpykit-0.1a0.dev202203161630.dist-info/RECORD
