Metadata-Version: 2.1
Name: ezpykit
Version: 0.1a0.dev202203161630
Summary: A easy, simple lib pack, based on python builtins and standard libraries.
Home-page: https://github.com/mo-han/mo-han-toolbox/tree/master/ezpykit
Author: mo-han
Author-email: zmhungrown@gmail.com
License: MIT
Platform: UNKNOWN
Classifier: License :: OSI Approved :: MIT License
Classifier: Programming Language :: Python
Classifier: Programming Language :: Python :: 3
Classifier: Programming Language :: Python :: 3.6
Classifier: Programming Language :: Python :: Implementation :: CPython
Classifier: Programming Language :: Python :: Implementation :: PyPy
Requires-Python: >=3.6.0
License-File: LICENSE
